df_louvain/__init__.py
df_louvain/df_louvain_cpp.cpython-311-darwin.so
df_louvain-0.1.5.dist-info/METADATA
df_louvain-0.1.5.dist-info/WHEEL
df_louvain-0.1.5.dist-info/licenses/LICENSE
df_louvain-0.1.5.dist-info/RECORD
