Metadata-Version: 2.2
Name: df-louvain
Version: 0.1.5
Summary: Python wrapper for DF-Louvain C++: Fast Incrementally Expanding Approach for Community Detection on Dynamic Graphs
Keywords: community detection,louvain,dynamic graphs,graph analysis,network analysis
Author: Subhajit Sahu (Original Author)
License: MIT License
Classifier: Development Status :: 3 - Alpha
Classifier: Intended Audience :: Science/Research
Classifier: Intended Audience :: Developers
Classifier: License :: OSI Approved :: MIT License
Classifier: Programming Language :: Python :: 3
Classifier: Programming Language :: Python :: 3.7
Classifier: Programming Language :: Python :: 3.8
Classifier: Programming Language :: Python :: 3.9
Classifier: Programming Language :: Python :: 3.10
Classifier: Programming Language :: Python :: 3.11
Classifier: Programming Language :: C++
Classifier: Operating System :: POSIX :: Linux
Classifier: Operating System :: MacOS :: MacOS X
Classifier: Operating System :: Microsoft :: Windows
Classifier: Topic :: Scientific/Engineering :: Information Analysis
Classifier: Topic :: Software Development :: Libraries :: Python Modules
Project-URL: Homepage, https://github.com/mcalapai/python-df-louvain
Project-URL: Repository, https://github.com/mcalapai/python-df-louvain
Requires-Python: >=3.7
Provides-Extra: test
Requires-Dist: pytest; extra == "test"
Provides-Extra: docs
Requires-Dist: sphinx>=4.0; extra == "docs"
Requires-Dist: sphinx-rtd-theme>=1.0; extra == "docs"
Requires-Dist: pybind11-stubgen>=0.14; extra == "docs"
Requires-Dist: myst-parser; extra == "docs"
